AUTHORS.md
LICENSE.md
README.md
pyproject.toml
setup.cfg
src/bmi_tester/__init__.py
src/bmi_tester/__main__.py
src/bmi_tester/_utils.py
src/bmi_tester/_version.py
src/bmi_tester/api.py
src/bmi_tester/main.py
src/bmi_tester.egg-info/PKG-INFO
src/bmi_tester.egg-info/SOURCES.txt
src/bmi_tester.egg-info/dependency_links.txt
src/bmi_tester.egg-info/entry_points.txt
src/bmi_tester.egg-info/requires.txt
src/bmi_tester.egg-info/top_level.txt
src/bmi_tester/_bootstrap/__init__.py
src/bmi_tester/_bootstrap/control_test.py
src/bmi_tester/_tests/__init__.py
src/bmi_tester/_tests/conftest.py
src/bmi_tester/_tests/stage_1/__init__.py
src/bmi_tester/_tests/stage_1/info_test.py
src/bmi_tester/_tests/stage_1/time_test.py
src/bmi_tester/_tests/stage_2/__init__.py
src/bmi_tester/_tests/stage_2/var_test.py
src/bmi_tester/_tests/stage_3/__init__.py
src/bmi_tester/_tests/stage_3/grid_test.py
src/bmi_tester/_tests/stage_3/grid_uniform_rectilinear_test.py
src/bmi_tester/_tests/stage_3/grid_unstructured_test.py
src/bmi_tester/_tests/stage_3/value_test.py