Metadata-Version: 2.4
Name: bmi_tester
Version: 0.5.10
Summary: Test Python BMI bindings
Author: Eric Hutton
Author-email: eric.hutton@colorado.edu
Maintainer: Eric Hutton, Mark Piper
Maintainer-email: eric.hutton@colorado.edu, mark.piper@colorado.edu
License: MIT
Project-URL: Changelog, https://github.com/csdms/bmi-tester/blob/master/CHANGES.rst
Project-URL: Documentation, https://bmi-tester.readthedocs.io/
Project-URL: Homepage, https://csdms.colorado.edu
Project-URL: Repository, https://github.com/csdms/bmi-tester
Keywords: bmi,csdms,model,python,testing
Classifier: Development Status :: 4 - Beta
Classifier: Intended Audience :: Science/Research
Classifier: License :: OSI Approved :: MIT License
Classifier: Operating System :: OS Independent
Classifier: Programming Language :: Python :: 3
Classifier: Programming Language :: Python :: 3.10
Classifier: Programming Language :: Python :: 3.11
Classifier: Programming Language :: Python :: 3.12
Classifier: Topic :: Scientific/Engineering :: Physics
Requires-Python: >=3.10
License-File: LICENSE.md
License-File: AUTHORS.md
Requires-Dist: importlib-resources; python_version < "3.12"
Requires-Dist: model-metadata>=0.8.1
Requires-Dist: numpy
Requires-Dist: pytest
Requires-Dist: pytest-dependency
Requires-Dist: standard-names>=0.2.8
Provides-Extra: units
Requires-Dist: gimli.units>=0.3.2; extra == "units"
Provides-Extra: dev
Requires-Dist: black; extra == "dev"
Requires-Dist: flake8; extra == "dev"
Requires-Dist: isort; extra == "dev"
Provides-Extra: testing
Requires-Dist: coveralls; extra == "testing"
Requires-Dist: pytest-cov; extra == "testing"
Requires-Dist: pytest>=3.6; extra == "testing"
Provides-Extra: docs
Requires-Dist: sphinx>=1.5.1; extra == "docs"
Provides-Extra: build
Requires-Dist: build; extra == "build"
Requires-Dist: twine; extra == "build"
Requires-Dist: zest.releaser; extra == "build"
Dynamic: license-file
